cryptobazen_statistics/__init__.py
cryptobazen_statistics/statistic_functions.py
cryptobazen_statistics-0.3.1.dist-info/LICENSE
cryptobazen_statistics-0.3.1.dist-info/METADATA
cryptobazen_statistics-0.3.1.dist-info/WHEEL
cryptobazen_statistics-0.3.1.dist-info/top_level.txt
cryptobazen_statistics-0.3.1.dist-info/RECORD
