Metadata-Version: 2.1
Name: cryptobazen_statistics
Version: 0.3.1
Summary: Statistic functions for Transformer models
Author: Cryptobazen
Author-email: erwinvink@outlook.com
License: MIT License
License-File: LICENSE
Requires-Dist: numpy >=1.24
Requires-Dist: scikit-learn >=1.2.0
